landcover_lca/database/__init__.py
landcover_lca/database/landcover_lca_database.db
landcover_lca/geo_goblin/__init__.py
landcover_lca/geo_goblin/geo_lca_emissions.py
landcover_lca/geo_goblin/geo_models.py
landcover_lca/geo_goblin/land_classes/__init__.py
landcover_lca/geo_goblin/land_classes/cropland.py
landcover_lca/geo_goblin/land_classes/forestland.py
landcover_lca/geo_goblin/land_classes/grassland.py
landcover_lca/geo_goblin/land_classes/landuse.py
landcover_lca/geo_goblin/land_classes/soc.py
landcover_lca/geo_goblin/land_classes/wetland.py
landcover_lca/land_classes/__init__.py
landcover_lca/land_classes/cropland.py
landcover_lca/land_classes/forestland.py
landcover_lca/land_classes/grassland.py
landcover_lca/land_classes/landuse.py
landcover_lca/land_classes/soc.py
landcover_lca/land_classes/wetland.py
landcover_lca/lca_emission.py
landcover_lca/models.py
landcover_lca/resource_manager/__init__.py
landcover_lca/resource_manager/data_loader.py
landcover_lca/resource_manager/database_manager.py
landcover_lca/resource_manager/landcover_data_manager.py
landcover_lca-0.2.1.dist-info/LICENSE
landcover_lca-0.2.1.dist-info/METADATA
landcover_lca-0.2.1.dist-info/WHEEL
landcover_lca-0.2.1.dist-info/RECORD
